{"kits":[{"name":"A mirror","kit_type":"ugc","is_featured":null,"created_at":"2021-02-08T12:14:43.390-08:00","updated_at":"2021-02-08T12:15:33.436-08:00","id":"1668395351859528594","kit_id":"1668395351859528594","user_id":"1564061799089701482","asset_bundles":[{"game_engine":"unity","game_engine_version":20194,"platform":"android","url":"https://cdn-content-ingress.altvr.com/artifacts/75/6b/756b4b341933920d9d183b691082e3c4-1668395351859528594_mirrorkit-android","description":null,"aasm_state":"active","created_at":"2021-02-08T12:15:33.399-08:00","updated_at":"2021-02-08T12:15:33.399-08:00","layout":null,"crc":"2556660230","client_cache_key":"756b4b341933920d9d183b691082e3c4","name":"1668395351859528594_mirrorkit","stereo_render_mode":null,"asset_bundle_id":"1668395771331870982","user_id":"1564061799089701482","asset_bundle_scene_id":"","avatar_id":""},{"game_engine":"unity","game_engine_version":20194,"platform":"pc","url":"https://cdn-content-ingress.altvr.com/artifacts/75/6b/756b4b341933920d9d183b691082e3c4-1668395351859528594_mirrorkit-pc","description":null,"aasm_state":"active","created_at":"2021-02-08T12:15:33.273-08:00","updated_at":"2021-02-08T12:15:33.273-08:00","layout":null,"crc":"803830117","client_cache_key":"756b4b341933920d9d183b691082e3c4","name":"1668395351859528594_mirrorkit","stereo_render_mode":null,"asset_bundle_id":"1668395770283294980","user_id":"1564061799089701482","asset_bundle_scene_id":"","avatar_id":""}],"image_original":null,"image_medium":null,"image_thumbnail":null},{"name":"GitAddDataAnim","kit_type":"ugc","is_featured":null,"created_at":"2021-02-18T04:33:32.719-08:00","updated_at":"2021-02-18T04:33:32.719-08:00","id":"1675410990734246894","kit_id":"1675410990734246894","user_id":"1564061799089701482","asset_bundles":[],"image_original":null,"image_medium":null,"image_thumbnail":null},{"name":"Mountain king Music","kit_type":"ugc","is_featured":null,"created_at":"2021-01-19T11:20:44.583-08:00","updated_at":"2021-01-19T11:43:25.715-08:00","id":"1653872668153217085","kit_id":"1653872668153217085","user_id":"1564061799089701482","asset_bundles":[{"game_engine":"unity","game_engine_version":20194,"platform":"android","url":"https://cdn-content-ingress.altvr.com/artifacts/b5/ed/b5ed8158fc84c7b41871dc28eef97666-musickit2-android","description":null,"aasm_state":"active","created_at":"2021-01-19T11:43:25.646-08:00","updated_at":"2021-01-19T11:43:25.646-08:00","layout":null,"crc":"2998705674","client_cache_key":"b5ed8158fc84c7b41871dc28eef97666","name":"musickit2","stereo_render_mode":null,"asset_bundle_id":"1653884085635907872","user_id":"1564061799089701482","asset_bundle_scene_id":"","avatar_id":""},{"game_engine":"unity","game_engine_version":20194,"platform":"pc","url":"https://cdn-content-ingress.altvr.com/artifacts/b5/ed/b5ed8158fc84c7b41871dc28eef97666-musickit2-pc","description":null,"aasm_state":"active","created_at":"2021-01-19T11:43:24.722-08:00","updated_at":"2021-01-19T11:43:24.722-08:00","layout":null,"crc":"3066278957","client_cache_key":"b5ed8158fc84c7b41871dc28eef97666","name":"musickit2","stereo_render_mode":null,"asset_bundle_id":"1653884077901611284","user_id":"1564061799089701482","asset_bundle_scene_id":"","avatar_id":""}],"image_original":null,"image_medium":null,"image_thumbnail":null},{"name":"Windmill sound","kit_type":"ugc","is_featured":null,"created_at":"2021-02-01T10:59:20.592-08:00","updated_at":"2021-02-01T10:59:20.592-08:00","id":"1663283981853918024","kit_id":"1663283981853918024","user_id":"1564061799089701482","asset_bundles":[],"image_original":null,"image_medium":null,"image_thumbnail":null},{"name":"cavemusic","kit_type":"ugc","is_featured":null,"created_at":"2021-01-19T10:51:37.045-08:00","updated_at":"2021-01-19T11:05:42.814-08:00","id":"1653858008725193067","kit_id":"1653858008725193067","user_id":"1564061799089701482","asset_bundles":[{"game_engine":"unity","game_engine_version":20194,"platform":"android","url":"https://cdn-content-ingress.altvr.com/artifacts/fc/32/fc32cab64c14f3a58642ade528d2a0d4-1653858008725193067_musickit-android","description":null,"aasm_state":"active","created_at":"2021-01-19T11:05:42.731-08:00","updated_at":"2021-01-19T11:05:42.731-08:00","layout":null,"crc":"1569129454","client_cache_key":"fc32cab64c14f3a58642ade528d2a0d4","name":"1653858008725193067_musickit","stereo_render_mode":null,"asset_bundle_id":"1653865102937424241","user_id":"1564061799089701482","asset_bundle_scene_id":"","avatar_id":""},{"game_engine":"unity","game_engine_version":20194,"platform":"pc","url":"https://cdn-content-ingress.altvr.com/artifacts/fc/32/fc32cab64c14f3a58642ade528d2a0d4-1653858008725193067_musickit-pc","description":null,"aasm_state":"active","created_at":"2021-01-19T11:05:42.007-08:00","updated_at":"2021-01-19T11:05:42.007-08:00","layout":null,"crc":"2250950257","client_cache_key":"fc32cab64c14f3a58642ade528d2a0d4","name":"1653858008725193067_musickit","stereo_render_mode":null,"asset_bundle_id":"1653865096780185966","user_id":"1564061799089701482","asset_bundle_scene_id":"","avatar_id":""}],"image_original":null,"image_medium":null,"image_thumbnail":null}],"pagination":{"page":1,"pages":1,"count":5}}